CryptoBotSyncApi/__init__.py
cryptobotsyncapi-1.0.1.dist-info/METADATA
cryptobotsyncapi-1.0.1.dist-info/WHEEL
cryptobotsyncapi-1.0.1.dist-info/licenses/LICENSE
cryptobotsyncapi-1.0.1.dist-info/RECORD
