Metadata-Version: 2.4
Name: CryptoBotSyncApi
Version: 1.0.1
Summary: Simple python library for CryptoBot (service CryptoPay) API
Project-URL: Github, https://github.com/Artcher19/CryptoBotSyncApi
Author: Artcher
License-File: LICENSE
Classifier: License :: OSI Approved :: MIT License
Classifier: Operating System :: OS Independent
Classifier: Programming Language :: Python :: 3
Requires-Python: >=3.10.0
